[
  {
    "slug": "matej-vais",
    "img": "/assets/imgs/team/matej-vais.webp",
    "instagram": "https://www.instagram.com/bigdogvais",
    "email": "vais@tdprod.cz",
    "phone": "+420 737 065 717",
    "name": "Matěj Vais",
    "subName": "Operace"
  },
  {
    "slug": "martin-studnicky",
    "img": "/assets/imgs/team/martin-studnicky.webp",
    "instagram": "https://www.instagram.com/_martinstudnicky_/",
    "email": "studnicky@tdprod.cz",
    "phone": "+420 722 575 804",
    "name": "Martin Studnický",
    "subName": "Produkce"
  },
  {
    "slug": "matyas-vanek",
    "img": "/assets/imgs/team/matyas-vanek.webp",
    "instagram": "https://www.instagram.com/_v.matyas_/",
    "email": "vanek@tdprod.cz",
    "phone": "+420 792 770 711",
    "name": "Matyáš Vaněk",
    "subName": "Design"
  },
  {
    "slug": "sebastian-vanek",
    "img": "/assets/imgs/team/sebastian-vanek.webp",
    "instagram": "https://www.instagram.com/sebe.jumps/",
    "email": "s.vanek@tdprod.cz",
    "phone": "+420 792 755 878",
    "name": "Sebastian Vaněk",
    "subName": "Marketing"
  },
  {
    "slug": "matej-turek",
    "img": "/assets/imgs/team/matej-turek.webp",
    "instagram": "https://www.instagram.com/matey_shoolin/",
    "email": "turek@tdprod.cz",
    "phone": "+420 732 735 908",
    "name": "Matěj Turek",
    "subName": "Sales"
  }
]